{
  "name": "checkbox-18",
  "type": "registry:example",
  "files": [
    {
      "path": "example/components/checkboxes/checkbox-18.tsx",
      "content": "import { Checkbox } from \"@/components/ui/checkbox\";\n\nconst items = [\n  { id: \"checkbox-18-c1\", value: \"c1\", label: \"Monday\", defaultChecked: true },\n  { id: \"checkbox-18-c2\", value: \"c2\", label: \"Tuesday\", defaultChecked: true },\n  { id: \"checkbox-18-c3\", value: \"c3\", label: \"Wednesday\" },\n  {\n    id: \"checkbox-18-c4\",\n    value: \"c4\",\n    label: \"Thursday\",\n    defaultChecked: true,\n  },\n  { id: \"checkbox-18-c5\", value: \"c5\", label: \"Friday\", defaultChecked: true },\n  { id: \"checkbox-18-c6\", value: \"c6\", label: \"Saturday\" },\n  { id: \"checkbox-18-c7\", value: \"c7\", label: \"Sunday\", disabled: true },\n];\n\nexport default function CheckboxDemo() {\n  return (\n    <fieldset className=\"space-y-4\">\n      <legend className=\"text-sm font-medium leading-none text-foreground\">\n        Days of the week\n      </legend>\n      <div className=\"flex gap-1.5\">\n        {items.map((item) => (\n          <label\n            key={item.id}\n            className=\"relative flex size-9 cursor-pointer flex-col items-center justify-center gap-3 rounded-full border border-input text-center shadow-sm shadow-black/5 outline-offset-2 transition-colors has-[[data-disabled]]:cursor-not-allowed has-[[data-state=checked]]:border-primary has-[[data-state=checked]]:bg-primary has-[[data-state=checked]]:text-primary-foreground has-[[data-disabled]]:opacity-50 has-[:focus-visible]:outline has-[:focus-visible]:outline-2 has-[:focus-visible]:outline-ring/70\"\n          >\n            <Checkbox\n              id={item.id}\n              value={item.value}\n              className=\"sr-only after:absolute after:inset-0\"\n              defaultChecked={item.defaultChecked}\n              disabled={item.disabled}\n            />\n            <span aria-hidden=\"true\" className=\"text-sm font-medium\">\n              {item.label[0]}\n            </span>\n            <span className=\"sr-only\">{item.label}</span>\n          </label>\n        ))}\n      </div>\n    </fieldset>\n  );\n}\n",
      "type": "registry:example",
      "target": ""
    }
  ]
}