{
  "name": "dropdown-03",
  "type": "registry:example",
  "files": [
    {
      "path": "example/components/dropdowns/dropdown-03.tsx",
      "content": "import { Bolt, ChevronDown, CopyPlus, Files, Layers2 } from \"lucide-react\";\n\nimport { Button } from \"@/components/ui/button\";\nimport {\n  DropdownMenu,\n  DropdownMenuContent,\n  DropdownMenuItem,\n  DropdownMenuTrigger,\n} from \"@/components/ui/dropdown-menu\";\n\nexport default function DropdownDemo() {\n  return (\n    <DropdownMenu>\n      <DropdownMenuTrigger asChild>\n        <Button variant=\"outline\">\n          Menu with icons\n          <ChevronDown\n            className=\"-me-1 ms-2 opacity-60\"\n            size={16}\n            strokeWidth={2}\n            aria-hidden=\"true\"\n          />\n        </Button>\n      </DropdownMenuTrigger>\n      <DropdownMenuContent>\n        <DropdownMenuItem>\n          <CopyPlus\n            size={16}\n            strokeWidth={2}\n            className=\"opacity-60\"\n            aria-hidden=\"true\"\n          />\n          Copy\n        </DropdownMenuItem>\n        <DropdownMenuItem>\n          <Bolt\n            size={16}\n            strokeWidth={2}\n            className=\"opacity-60\"\n            aria-hidden=\"true\"\n          />\n          Edit\n        </DropdownMenuItem>\n        <DropdownMenuItem>\n          <Layers2\n            size={16}\n            strokeWidth={2}\n            className=\"opacity-60\"\n            aria-hidden=\"true\"\n          />\n          Group\n        </DropdownMenuItem>\n        <DropdownMenuItem>\n          <Files\n            size={16}\n            strokeWidth={2}\n            className=\"opacity-60\"\n            aria-hidden=\"true\"\n          />\n          Clone\n        </DropdownMenuItem>\n      </DropdownMenuContent>\n    </DropdownMenu>\n  );\n}\n",
      "type": "registry:example",
      "target": ""
    }
  ]
}