{
  "name": "input-02",
  "type": "registry:example",
  "files": [
    {
      "path": "example/components/inputs/input-02.tsx",
      "content": "import { Input } from \"@/components/ui/input\";\nimport { Label } from \"@/components/ui/label\";\n\nexport default function InputDemo() {\n  return (\n    <div className=\"space-y-2\">\n      <Label htmlFor=\"input-02\">\n        Required input <span className=\"text-destructive\">*</span>\n      </Label>\n      <Input id=\"input-02\" placeholder=\"Email\" type=\"email\" required />\n    </div>\n  );\n}\n",
      "type": "registry:example",
      "target": ""
    }
  ]
}